wexample_api-0.0.83.dist-info/METADATA
wexample_api-0.0.83.dist-info/WHEEL
wexample_api-0.0.83.dist-info/entry_points.txt
wexample_api/__init__.py
wexample_api/__pycache__/__init__.py
wexample_api/client/__init__.py
wexample_api/common/__init__.py
wexample_api/common/__pycache__/__init__.py
wexample_api/common/abstract_gateway.py
wexample_api/common/http_request_payload.py
wexample_api/const/__init__.py
wexample_api/const/__pycache__/__init__.py
wexample_api/const/http.py
wexample_api/demo/__init__.py
wexample_api/demo/demo_simple_gateway.py
wexample_api/enums/__init__.py
wexample_api/enums/__pycache__/__init__.py
wexample_api/enums/http.py
wexample_api/errors/__init__.py
wexample_api/errors/gateway_authentication_error.py
wexample_api/errors/gateway_connexion_error.py
wexample_api/middleware/__init__.py
wexample_api/models/__init__.py
wexample_api/py.typed
wexample_api-0.0.83.dist-info/RECORD
